CoinbaseAPI/CoinbaseAPI.py
CoinbaseAPI/__init__.py
CoinbaseAPI-1.1.dist-info/METADATA
CoinbaseAPI-1.1.dist-info/WHEEL
CoinbaseAPI-1.1.dist-info/top_level.txt
CoinbaseAPI-1.1.dist-info/RECORD
