Metadata-Version: 2.1
Name: CoinbaseAPI
Version: 1.1
Summary: Easy Coinbase API for simple payment acceptance
Home-page: https://github.com/billiedark/CoinbaseAPI
Author: billiedark
Author-email: hhxx213@gmail.com
License: UNKNOWN
Platform: UNKNOWN
Classifier: Programming Language :: Python :: 3
Classifier: License :: OSI Approved :: MIT License
Classifier: Operating System :: OS Independent
Requires-Python: >=3.6
